RecursionTree/Excalibur-Monospace.ttf
RecursionTree/__init__.py
RecursionTree/decorator.py
RecursionTree/graphics.py
RecursionTree/main.py
RecursionTree/node.py
RecursionTree/settings.py
RecursionTree-2.0.dist-info/LICENSE
RecursionTree-2.0.dist-info/METADATA
RecursionTree-2.0.dist-info/WHEEL
RecursionTree-2.0.dist-info/top_level.txt
RecursionTree-2.0.dist-info/RECORD
