Metadata-Version: 2.1
Name: RecursionTree
Version: 2.0
Summary: Builds recursive calls tree and saves it as an SVG file.
Home-page: https://github.com/IgorZyktin/recursion_tree
Author: Igor Zyktin
Author-email: nicord@yandex.ru
License: UNKNOWN
Platform: UNKNOWN
Classifier: Programming Language :: Python :: 3
Classifier: License :: OSI Approved :: MIT License
Classifier: Operating System :: OS Independent
